wristband/py.typed
wristband/django_auth/__init__.py
wristband/django_auth/auth.py
wristband/django_auth/client.py
wristband/django_auth/config_resolver.py
wristband/django_auth/data_encryptor.py
wristband/django_auth/exceptions.py
wristband/django_auth/models.py
wristband/django_auth/utils.py
wristband/django_auth/backends/__init__.py
wristband/django_auth/backends/auth/__init__.py
wristband/django_auth/backends/auth/default_wristband_auth_backend_adapter.py
wristband/django_auth/backends/auth/wristband_auth_backend.py
wristband/django_auth/sessions/session_helpers.py
wristband/django_auth/sessions/backends/encrypted_cookies.py
wristband_django_auth-1.0.1.dist-info/licenses/LICENSE
wristband_django_auth-1.0.1.dist-info/METADATA
wristband_django_auth-1.0.1.dist-info/WHEEL
wristband_django_auth-1.0.1.dist-info/top_level.txt
wristband_django_auth-1.0.1.dist-info/RECORD
