Metadata-Version: 2.4
Name: wristband-django-auth
Version: 1.0.1
Summary: SDK for integrating your Python Django application with Wristband. Handles user authentication, session management, and token management. Optional Django Rest Framework (DRF) support included.
Author-email: Wristband <support@wristband.dev>
License-Expression: MIT
Project-URL: Homepage, https://wristband.dev
Project-URL: Repository, https://github.com/wristband-dev/django-auth
Project-URL: Documentation, https://docs.wristband.dev
Keywords: api,auth,authentication,authorization,django,jwt,multi-tenant,multi-tenancy,oauth,oidc,sdk,secure,security,sso,wristband
Classifier: Programming Language :: Python :: 3
Classifier: Programming Language :: Python :: 3.10
Classifier: Programming Language :: Python :: 3.11
Classifier: Programming Language :: Python :: 3.12
Classifier: Programming Language :: Python :: 3.13
Classifier: Programming Language :: Python :: 3.14
Classifier: Operating System :: OS Independent
Classifier: Intended Audience :: Developers
Classifier: Topic :: Software Development :: Libraries :: Python Modules
Classifier: Topic :: Security
Classifier: Development Status :: 4 - Beta
Classifier: Framework :: Django
Classifier: Framework :: Django :: 4.2
Classifier: Framework :: Django :: 5.0
Classifier: Framework :: Django :: 5.1
Classifier: Framework :: Django :: 5.2
Requires-Python: >=3.10
License-File: LICENSE
Requires-Dist: cryptography>=44.0.3
Requires-Dist: Django>=4.2
Requires-Dist: httpx>=0.24.0
Requires-Dist: wristband-python-jwt==0.1.0
Provides-Extra: drf
Requires-Dist: djangorestframework>=3.15.0; extra == "drf"
Provides-Extra: all
Requires-Dist: djangorestframework>=3.15.0; extra == "all"
Provides-Extra: dev
Requires-Dist: djangorestframework>=3.15.0; extra == "dev"
Requires-Dist: setuptools>=61; extra == "dev"
Requires-Dist: pytest<9.0.0,>=8.2.0; extra == "dev"
Requires-Dist: pytest-cov<6.0.0,>=5.0.0; extra == "dev"
Requires-Dist: pytest-httpx>=0.21.0; extra == "dev"
Requires-Dist: mypy>=1.10.0; extra == "dev"
Requires-Dist: types-jsonschema; extra == "dev"
Requires-Dist: django-stubs; extra == "dev"
Requires-Dist: flake8<7.0.0,>=6.0.0; extra == "dev"
Requires-Dist: flake8-pyproject>=1.2.0; extra == "dev"
Requires-Dist: pip-audit>=2.0.0; extra == "dev"
Requires-Dist: bandit>=1.7.0; extra == "dev"
Requires-Dist: build>=0.10.0; extra == "dev"
Requires-Dist: twine>=4.0.0; extra == "dev"
Requires-Dist: black>=23.0.0; extra == "dev"
Requires-Dist: isort>=5.12.0; extra == "dev"
Dynamic: license-file
